sntn/__init__.py
sntn/__main__.py
sntn/_bvn.py
sntn/_fast_integrals.py
sntn/_lasso.py
sntn/_nts.py
sntn/_screening.py
sntn/_solvers.py
sntn/_split.py
sntn/_tnorm.py
sntn/dists.py
sntn/posi.py
sntn/trialML.py
sntn/_cdf_bvn/__init__.py
sntn/_cdf_bvn/_approx.py
sntn/_cdf_bvn/_brute.py
sntn/_cdf_bvn/_utils.py
sntn/benchmark/readme.md
sntn/benchmark/runtime.py
sntn/utilities/__init__.py
sntn/utilities/grad.py
sntn/utilities/linear.py
sntn/utilities/utils.py
sntn-0.1.0.dist-info/LICENSE.txt
sntn-0.1.0.dist-info/METADATA
sntn-0.1.0.dist-info/WHEEL
sntn-0.1.0.dist-info/top_level.txt
sntn-0.1.0.dist-info/RECORD
