Metadata-Version: 2.1
Name: sntn
Version: 0.1.0
Summary: Sum of a normal and a truncated Normal (SNTN)
Home-page: https://github.com/ErikinBC/SNTN
Author: Erik Drysdale
Author-email: erikinwest@gmail.com
License: GPLv3
Classifier: Development Status :: 3 - Alpha
Classifier: Intended Audience :: Science/Research
Classifier: License :: OSI Approved :: MIT License
Classifier: Operating System :: POSIX :: Linux
Classifier: Programming Language :: Python :: 3
Requires-Python: >=3.10.0, <=3.11.9
License-File: LICENSE.txt
Requires-Dist: plotnine >=0.12.1
Requires-Dist: numpy >=1.25.0
Requires-Dist: pandas >=1.5.3
Requires-Dist: scikit-learn >=1.2.2
Requires-Dist: scipy >=1.10.1
Requires-Dist: statsmodels >=0.14.0
